tidal_scraper/cli.py
tidal_scraper/download.py
tidal_scraper/helper.py
tidal_scraper/metadata.py
tidal_scraper/state.py
tidal_scraper-1.0.dist-info/METADATA
tidal_scraper-1.0.dist-info/WHEEL
tidal_scraper-1.0.dist-info/entry_points.txt
tidal_scraper-1.0.dist-info/licenses/LICENSE
tidal_scraper-1.0.dist-info/RECORD
